{"type":"website","image":"https://ozksgdmyrqcxcwhnbepg.supabase.co/storage/v1/object/public/assets/4503/d3481944-89a0-440b-8b02-f078c55b53e1","title":"MIRA.LC","favicon":"https://ozksgdmyrqcxcwhnbepg.supabase.co/storage/v1/object/public/assets/4503/320c7832-a960-437d-843f-78f77440150c","description":"Transforme suas Conversas, Transforma seus Resultados.","__resolveType":"website/sections/Seo/Seo.tsx","titleTemplate":"MIRA.LC","descriptionTemplate":"Transforme suas Conversas, Transforma seus Resultados."}